gala_fj/__init__.py
gala_fj/cache_files/attn_is_all_you_need.pdf_embedding_type=azure_semantic/bm25_index.pkl
gala_fj/cache_files/attn_is_all_you_need.pdf_embedding_type=azure_semantic/chromadb/ca39055d-93a5-489c-9889-fd815c5138bf/data_level0.bin
gala_fj/cache_files/attn_is_all_you_need.pdf_embedding_type=azure_semantic/chromadb/ca39055d-93a5-489c-9889-fd815c5138bf/header.bin
gala_fj/cache_files/attn_is_all_you_need.pdf_embedding_type=azure_semantic/chromadb/ca39055d-93a5-489c-9889-fd815c5138bf/length.bin
gala_fj/cache_files/attn_is_all_you_need.pdf_embedding_type=azure_semantic/chromadb/ca39055d-93a5-489c-9889-fd815c5138bf/link_lists.bin
gala_fj/cache_files/attn_is_all_you_need.pdf_embedding_type=azure_semantic/chromadb/chroma.sqlite3
gala_fj/cache_files/attn_is_all_you_need.pdf_embedding_type=azure_semantic/chunk_wise_triples/0.txt
gala_fj/cache_files/attn_is_all_you_need.pdf_embedding_type=azure_semantic/chunk_wise_triples/1.txt
gala_fj/cache_files/attn_is_all_you_need.pdf_embedding_type=azure_semantic/chunk_wise_triples/10.txt
gala_fj/cache_files/attn_is_all_you_need.pdf_embedding_type=azure_semantic/chunk_wise_triples/11.txt
gala_fj/cache_files/attn_is_all_you_need.pdf_embedding_type=azure_semantic/chunk_wise_triples/12.txt
gala_fj/cache_files/attn_is_all_you_need.pdf_embedding_type=azure_semantic/chunk_wise_triples/13.txt
gala_fj/cache_files/attn_is_all_you_need.pdf_embedding_type=azure_semantic/chunk_wise_triples/14.txt
gala_fj/cache_files/attn_is_all_you_need.pdf_embedding_type=azure_semantic/chunk_wise_triples/15.txt
gala_fj/cache_files/attn_is_all_you_need.pdf_embedding_type=azure_semantic/chunk_wise_triples/16.txt
gala_fj/cache_files/attn_is_all_you_need.pdf_embedding_type=azure_semantic/chunk_wise_triples/17.txt
gala_fj/cache_files/attn_is_all_you_need.pdf_embedding_type=azure_semantic/chunk_wise_triples/18.txt
gala_fj/cache_files/attn_is_all_you_need.pdf_embedding_type=azure_semantic/chunk_wise_triples/2.txt
gala_fj-0.1.0.dist-info/METADATA
gala_fj-0.1.0.dist-info/WHEEL
gala_fj-0.1.0.dist-info/RECORD
