Metadata-Version: 2.1
Name: gala_fj
Version: 0.1.0
Summary: 
Author: Parth Thakkar
Author-email: parth.thakkar@fujitsu.com
Requires-Python: >=3.9,<4.0
Classifier: Programming Language :: Python :: 3
Classifier: Programming Language :: Python :: 3.9
Classifier: Programming Language :: Python :: 3.10
Classifier: Programming Language :: Python :: 3.11
Classifier: Programming Language :: Python :: 3.12
Classifier: Programming Language :: Python :: 3.13
Requires-Dist: bs4 (>=0.0.2,<0.0.3)
Requires-Dist: chromadb (>=0.5.23,<0.6.0)
Requires-Dist: docling (>=2.12.0,<3.0.0)
Requires-Dist: docling-core (>=2.10.0,<3.0.0)
Requires-Dist: langchain (>=0.3.12,<0.4.0)
Requires-Dist: langchain-cohere (>=0.3.3,<0.4.0)
Requires-Dist: langchain-community (>=0.3.12,<0.4.0)
Requires-Dist: langchain-experimental (>=0.3.3,<0.4.0)
Requires-Dist: langchain-google-genai (>=2.0.7,<3.0.0)
Requires-Dist: langchain-groq (>=0.2.1,<0.3.0)
Requires-Dist: langchain-openai (>=0.2.12,<0.3.0)
Requires-Dist: langchain-text-splitters (>=0.3.3,<0.4.0)
Requires-Dist: neo4j (>=5.27.0,<6.0.0)
Requires-Dist: nltk (>=3.9.1,<4.0.0)
Requires-Dist: poetry-dotenv (>=0.4.0,<0.5.0)
Requires-Dist: rank-bm25 (>=0.2.2,<0.3.0)
Requires-Dist: requests (>=2.32.3,<3.0.0)
Requires-Dist: tqdm (>=4.67.1,<5.0.0)
Requires-Dist: validators (>=0.34.0,<0.35.0)
Requires-Dist: yacs (>=0.1.8,<0.2.0)
